examples/__init__.py
examples/example.py
examples/lcd_example.py
pyArduino/__init__.py
pyArduino/lcd_control.py
pyArduino/pyArduino.py
tests/__init__.py
pyArduino-0.2.2.dist-info/LICENSE
pyArduino-0.2.2.dist-info/METADATA
pyArduino-0.2.2.dist-info/WHEEL
pyArduino-0.2.2.dist-info/top_level.txt
pyArduino-0.2.2.dist-info/RECORD
