Metadata-Version: 2.1
Name: pyArduino
Version: 0.2.2
Summary: Python module to handle Arduino port serial comunication
Home-page: https://github.com/Pyryzyab/pyArduino
Author: Alex Vergara
Author-email: pyryzyab@tutanota.com
License: UNKNOWN
Platform: UNKNOWN
Classifier: Programming Language :: Python :: 3
Classifier: License :: OSI Approved :: MIT License
Classifier: Operating System :: OS Independent
Requires-Python: >=3.8
Requires-Dist: pyserial
Requires-Dist: pyfirmata
